Workbook

Sheet BOM Summary
A1: Portenta – RPi5 – Jetson LoRa Backbone — Bill of Materials
A3: Report Title | B3: Portenta → RPi5 → Jetson Nano LoRa Backbone BOM
A4: Revision | B4: v2.0
A5: Generated | B5: May 15, 2026
A6: Currency | B6: USD
A7: Notes | B7: All prices are current as of May 2026. Raspberry Pi 5 reflects Feb 2026 price hike. Jetson Nano 4GB is EOL; Orin Nano Super recommended as successor. Prices exclude applicable taxes, duties, and shipping.
A9: BOM Summary — Per-Unit System Build
A10: Section | B10: # Line Items | C10: Subtotal (USD) | D10: Hardware Only? | E10: Sheet Reference | F10: Notes
A11: Compute | B11: 9 | C11: ='Compute'!G12 | D11: Yes | E11: Compute | F11: Core processing backbone
A12: LoRa / Gateway | B12: 9 | C12: ='LoRa-Gateway'!G12 | D12: Yes | E12: LoRa-Gateway | F12: RF infrastructure
A13: Power | B13: 8 | C13: ='Power'!G11 | D13: Yes | E13: Power | F13: Distribution and off-grid
A14: Networking / Uplink | B14: 6 | C14: ='Networking-Uplink'!G9 | D14: No — see notes | E14: Networking-Uplink | F14: Backhaul and connectivity — excludes Starlink monthly service ($50/mo)
A15: Mechanical / Environmental | B15: 9 | C15: ='Mechanical-Env'!G12 | D15: Yes | E15: Mechanical-Env | F15: Enclosures and mounting
A16: TOTAL | B16: 41 | C16: =SUM(C11:C15)-'Networking-Uplink'!G4 | D16: Hardware Only | E16: All Sheets | F16: Per-unit system build — grand total hardware only (Starlink $50/mo service plan excluded)
A18: ⚠ Note: Starlink Roam service plan ($50/mo) is a recurring cost and is EXCLUDED from all hardware subtotals and the grand total. Prices as of May 2026. Taxes, duties, and shipping not included.

Sheet Compute
A1: Compute Hardware — Arduino Portenta / Raspberry Pi 5 / Jetson Orin Nano Super
A2: Line # | B2: Part Name | C2: Part Number / SKU | D2: Description | E2: Qty | F2: Unit Price (USD) | G2: Extended Price (USD) | H2: Supplier | I2: Supplier URL | J2: Lead Time | K2: Notes
A3: 1 | B3: Arduino Portenta X8 | C3: ABX00049 | D3: Industrial 9-core SoM: NXP i.MX 8M Mini (4x Cortex-A53 @1.8GHz + M4) + STM32H747 dual M7/M4. Linux + Arduino RTOS, Wi-Fi/BT, PSA certified | E3: 1 | F3: 321 | G3: =E3*F3 | H3: Arduino Official Store | I3: store.arduino.cc | J3: 1–3 days | K3: Field edge MCU / sensor aggregator; acts as LoRa node host
A4: 2 | B4: Arduino Portenta H7 | C4: ABX00042 | D4: Dual-core STM32H747: Cortex-M7 @480MHz + M4 @240MHz. 8MB SDRAM, 16MB Flash, Wi-Fi, BT 5.1 | E4: 1 | F4: 105 | G4: =E4*F4 | H4: Amazon / Arduino Store | I4: amazon.com | J4: 1–5 days | K4: Real-time co-processor for sensor I/O and deterministic control loops
A5: 3 | B5: Raspberry Pi 5 — 8GB | C5: SC1111 | D5: BCM2712 quad-core Cortex-A76 @2.4GHz, 8GB LPDDR4X, PCIe Gen 2, dual 4K display, USB 3.0 | E5: 1 | F5: 125 | G5: =E5*F5 | H5: PiShop / Adafruit | I5: pishop.us | J5: In stock | K5: Mid-tier gateway host; runs ChirpStack NS, MQTT broker, data pipeline. Price reflects Feb 2026 hike.
A6: 4 | B6: RPi5 Active Cooler | C6: SC1148 | D6: Official heatsink + blower fan for RPi5; clips to SoC directly | E6: 1 | F6: 5 | G6: =E6*F6 | H6: PiShop / Adafruit | I6: pishop.us | J6: In stock | K6: Required for sustained full-load operation
A7: 5 | B7: Samsung 256GB microSD (A2, V30) | C7: MB-MC256KA | D7: UHS-I U3 A2 microSD; rated for random read/write on SBC workloads | E7: 1 | F7: 22 | G7: =E7*F7 | H7: Amazon | I7: amazon.com | J7: Next-day | K7: Boot + OS media for RPi5
A8: 6 | B8: NVIDIA Jetson Orin Nano Super 8GB Dev Kit | C8: 945-13767-0003-000 | D8: 8-core Arm Cortex-A78AE, 1024-core Ampere GPU, 67 TOPS AI, 8GB LPDDR5, replaces EOL Jetson Nano 4GB | E8: 1 | F8: 249 | G8: =E8*F8 | H8: NVIDIA / Seeed Studio | I8: seeedstudio.com | J8: 3–7 days | K8: Primary AI inference node; backbone top-tier compute. Jetson Nano 4GB is EOL — Orin Nano Super is the current-gen successor.
A9: 7 | B9: WD Blue SN580 NVMe SSD 500GB | C9: WDS500G3B0E | D9: PCIe Gen 4 M.2 2242; high endurance for edge logging and model storage | E9: 1 | F9: 45 | G9: =E9*F9 | H9: Amazon | I9: amazon.com | J9: Next-day | K9: Storage for Jetson Orin Nano Super via M.2 slot
A10: 8 | B10: Waveshare CM4/RPi5 PoE+ HAT | C10: Waveshare PoE+ HAT-B | D10: 802.3at PoE+ HAT for RPi5; provides 5V/4A from 48V PoE line, onboard fan header | E10: 1 | F10: 28 | G10: =E10*F10 | H10: Waveshare / Amazon | I10: waveshare.com | J10: 5–10 days | K10: Eliminates separate RPi5 power adapter when PoE switch is present
A11: 9 | B11: USB-C GaN Charger 65W | C11: Anker 735 or equiv. | D11: 65W 3-port GaN charger; USB-C PD for Portenta X8 / H7 bench supply | E11: 1 | F11: 40 | G11: =E11*F11 | H11: Amazon | I11: amazon.com | J11: Next-day | K11: Bench / staging power for Portenta boards; field units use regulated DIN-rail supply
B12: SECTION TOTAL | G12: =SUM(G3:G11)

Sheet LoRa-Gateway
A1: LoRa & Gateway Hardware — RF Infrastructure & Antenna
A2: Line # | B2: Part Name | C2: Part Number / SKU | D2: Description | E2: Qty | F2: Unit Price (USD) | G2: Extended Price (USD) | H2: Supplier | I2: Supplier URL | J2: Lead Time | K2: Notes
A3: 1 | B3: RAKwireless WisGate Edge Pro (Outdoor) | C3: RAK7289V2 | D3: 8-ch outdoor LoRaWAN gateway, Semtech SX1303, IP67, Wi-Fi/Eth/LTE-optional, GPS, WisGateOS 2, PoE | E3: 1 | F3: 382 | G3: =E3*F3 | H3: RAKwireless Store | I3: store.rakwireless.com | J3: 5–10 days | K3: Primary field gateway; antenna sold separately (see row 7)
A4: 2 | B4: RAKwireless WisGate Edge Lite 2 (Indoor) | C4: RAK7268V2 | D4: 8-ch indoor LoRaWAN gateway, SX1303, Wi-Fi/Eth, PoE, WisGateOS 2, OpenVPN/WireGuard | E4: 1 | F4: 194 | G4: =E4*F4 | H4: RAKwireless Store / Rokland | I4: rokland.com | J4: In stock (US) | K4: Indoor lab / base station gateway; runs ChirpStack in built-in mode
A5: 3 | B5: Dragino LPS8N Indoor Gateway | C5: LPS8N-915 | D5: 8-ch LoRaWAN indoor gateway, SX1302/SX1303, Eth + Wi-Fi, open-source OpenWRT firmware | E5: 1 | F5: 157 | G5: =E5*F5 | H5: Dragino Store | I5: dragino.com | J5: In stock | K5: Budget redundant/backup indoor gateway option
A6: 4 | B6: Waveshare SX1262 LoRa HAT for RPi | C6: SX1262 LORAWAN HAT | D6: SX1262 868/915MHz HAT for Raspberry Pi, SPI interface, 22dBm TX, onboard antenna / SMA | E6: 1 | F6: 28 | G6: =E6*F6 | H6: Waveshare / Amazon | I6: waveshare.com | J6: 5–10 days | K6: Attaches to RPi5 to act as a LoRa concentrator endpoint or range test node
A7: 5 | B7: EBYTE E22-900M30S LoRa Module (SX1262) | C7: E22-900M30S | D7: SX1262-based 915MHz module, 30dBm (1W) TX power, SPI, -147dBm sensitivity, SMD | E7: 3 | F7: 12 | G7: =E7*F7 | H7: EBYTE / AliExpress | I7: ebyte.com | J7: 7–14 days | K7: Node-side LoRa transceivers for Portenta X8 breakout or sensor nodes (qty 3)
A8: 6 | B8: Seeed Studio Grove LoRa E5 Module | C8: 113020091 | D8: LoRa-E5 (STM32WLE5JC) 915MHz module; LoRaWAN Class A/B/C, AT command, 3.3V, ultra-compact | E8: 2 | F8: 18 | G8: =E8*F8 | H8: Seeed Studio | I8: seeedstudio.com | J8: 5–7 days | K8: Compact MCU+LoRa combo for low-power remote sensor nodes (qty 2)
A9: 7 | B9: 915MHz 8dBi Fiberglass Omni Antenna | C9: Taoglas FW.81 or equiv. | D9: 900–930MHz fiberglass omni, 8dBi gain, N-male, 1.2m, IP65, mast-mount | E9: 1 | F9: 55 | G9: =E9*F9 | H9: Rokland / Taoglas | I9: rokland.com | J9: 3–7 days | K9: Primary gateway antenna; mount on mast above enclosure
A10: 8 | B10: 915MHz 5dBi Omni Antenna (short) | C10: Cloudpower / equiv. | D10: 915MHz fiberglass omni, 5dBi, N-male, ~32cm, IP65, includes LMR-100 pigtail | E10: 2 | F10: 45 | G10: =E10*F10 | H10: Amazon | I10: amazon.com | J10: 3–10 days | K10: Secondary / node antennas (qty 2); one per remote node or indoor gateway
A11: 9 | B11: LMR-400 Coax Jumper 5m N-Male to N-Male | C11: Times Microwave / equiv. | D11: Low-loss coax, 0.5dB/10m @900MHz, weatherproofed N-male connectors, 5m | E11: 1 | F11: 32 | G11: =E11*F11 | H11: Rokland / Times Microwave | I11: timesmicrowave.com | J11: 3–7 days | K11: Feed line from gateway enclosure to mast-mounted 8dBi antenna
B12: SECTION TOTAL | G12: =SUM(G3:G11)

Sheet Power
A1: Power Distribution & Off-Grid Energy
A2: Line # | B2: Part Name | C2: Part Number / SKU | D2: Description | E2: Qty | F2: Unit Price (USD) | G2: Extended Price (USD) | H2: Supplier | I2: Supplier URL | J2: Lead Time | K2: Notes
A3: 1 | B3: Mean Well XTR-480-12 DIN Rail PSU | C3: XTR-480-12 | D3: 3-phase 320–600VAC input, 12VDC/30A (360W) output, 95.5% efficient, -40°C to +85°C, IP20, fanless | E3: 1 | F3: 123.5 | G3: =E3*F3 | H3: Jameco / Mouser | I3: jameco.com | J3: In stock | K3: Primary DIN-rail power supply for 12V backbone rail
A4: 2 | B4: Mean Well MDR-60-12 DIN Rail PSU | C4: MDR-60-12 | D4: 85–264VAC input, 12VDC/5A (60W), DIN rail, slim form factor, single-phase | E4: 1 | F4: 20.3 | G4: =E4*F4 | H4: Jameco / Mouser | I4: jameco.com | J4: In stock | K4: Secondary/redundant supply or remote node 12V feed
A5: 3 | B5: Victron SmartSolar MPPT 75/15 | C5: SCC075015060R | D5: 75V PV input, 15A charge current, Li/AGM/LiFePO4, Bluetooth, VictronConnect app | E5: 1 | F5: 82 | G5: =E5*F5 | H5: Victron Distributors | I5: victronenergy.com | J5: 5–7 days | K5: Solar charge controller for off-grid operation option
A6: 4 | B6: 100W Monocrystalline Solar Panel | C6: Renogy RNG-100D-SS | D6: 100W, 18.9Voc, MC4 connectors, aluminum frame, 0°C to +85°C storage | E6: 1 | F6: 95 | G6: =E6*F6 | H6: Renogy / Amazon | I6: renogy.com | J6: 5–10 days | K6: Optional off-grid solar input for remote sites
A7: 5 | B7: Battle Born LiFePO4 Battery 100Ah 12V | C7: BB10012 | D7: 100Ah lithium iron phosphate, built-in BMS, -20°C to +60°C, cycle life >3000 | E7: 1 | F7: 949 | G7: =E7*F7 | H7: Battle Born Batteries | I7: battlebornbatteries.com | J7: 3–7 days | K7: Optional off-grid energy storage; replaces 3x 35Ah AGM at same footprint
A8: 6 | B8: 802.3at PoE+ Injector 48V/30W | C8: TP-Link TL-POE160S | D8: Single-port 802.3at PoE+ injector; powers RPi5 HAT, indoor gateway, IP cameras | E8: 2 | F8: 18 | G8: =E8*F8 | H8: Amazon / TP-Link | I8: amazon.com | J8: Next-day | K8: Powers RPi5 PoE HAT and RAK7268 indoor gateway (qty 2)
A9: 7 | B9: DC-DC Buck Converter 12V→5V 15A | C9: Drok / equiv. | D9: Synchronous buck, 9–36V in, 5V/15A out, 75W, screw terminals, potentiometer adj. | E9: 2 | F9: 13 | G9: =E9*F9 | H9: Amazon | I9: amazon.com | J9: Next-day | K9: Steps 12V rail down to 5V for USB-powered nodes and sensors (qty 2)
A10: 8 | B10: Automotive Fuse Block 12-Way + Bus Bar | C10: Blue Sea 5026 or equiv. | D10: 12-position ATC fuse block, common ground bus, 30A rated, marine/RV grade | E10: 1 | F10: 28 | G10: =E10*F10 | H10: Amazon / West Marine | I10: amazon.com | J10: Next-day | K10: Per-circuit protection and distribution on 12V backbone rail
B11: SECTION TOTAL | G11: =SUM(G3:G10)

Sheet Networking-Uplink
A1: Networking & Uplink — Backhaul & Connectivity
A2: Line # | B2: Part Name | C2: Part Number / SKU | D2: Description | E2: Qty | F2: Unit Price (USD) | G2: Extended Price (USD) | H2: Supplier | I2: Supplier URL | J2: Lead Time | K2: Notes
A3: 1 | B3: Starlink Mini Dish | C3: Starlink Mini Kit | D3: Compact 12×10in phased array dish, 50–100Mbps down, <100ms latency, Wi-Fi 6 integrated, 30W, portable | E3: 1 | F3: 299 | G3: =E3*F3 | H3: Starlink (SpaceX) | I3: starlink.com | J3: 1–3 weeks | K3: Primary LEO satellite backhaul; service plan ~$50/mo (not included in BOM). Hardware price as of Oct 2025.
A4: 2 | B4: Starlink Roam Service (Monthly) | C4: Service plan | D4: Mobile/Roam data plan; unlimited deprioritized data; paused when not in use; ~$50/mo | E4: 1 | F4: 50 | G4: =E4*F4 | H4: Starlink | I4: starlink.com | J4: Instant activation | K4: Monthly recurring — NOT included in one-time hardware subtotal.
A5: 3 | B5: GL.iNet Beryl AX (GL-MT3000) Travel Router | C5: GL-MT3000 | D5: Wi-Fi 6 tri-band travel router, WireGuard/OpenVPN built-in, 1Gbps Eth, USB 3.0, OpenWrt | E5: 1 | F5: 80 | G5: =E5*F5 | H5: GL.iNet / Amazon | I5: gl-inet.com | J5: Next-day | K5: WAN aggregator / VPN concentrator between Starlink and backbone LAN
A6: 4 | B6: Teltonika RUT241 LTE Router | C6: RUT241 | D6: Cat 4 LTE, dual SIM failover, 1x Eth WAN, Wi-Fi 4, -40°C to +75°C, DIN-mountable | E6: 1 | F6: 185 | G6: =E6*F6 | H6: Teltonika Networks | I6: teltonika-networks.com | J6: 5–10 days | K6: LTE cellular failover uplink; auto-fails over from Starlink on outage
A7: 5 | B7: Outdoor Cat6A Ethernet Cable 30m | C7: Ubiquiti TC-PRO-30M or equiv. | D7: Direct-burial shielded Cat6A, 30m, UV-resistant jacket, 10GbE rated | E7: 1 | F7: 30 | G7: =E7*F7 | H7: Ubiquiti / Amazon | I7: amazon.com | J7: Next-day | K7: Gateway-to-compute trunk between outdoor enclosure and indoor backbone
A8: 6 | B8: Cisco Catalyst IE3100 Industrial Switch | C8: IE-3100-8T2C-E | D8: 8-port 10/100/1000T + 2x SFP combo, DIN-rail, -40°C to +70°C, IP30, PoE budget 60W | E8: 1 | F8: 420 | G8: =E8*F8 | H8: Cisco / CDW | I8: cisco.com | J8: 7–14 days | K8: Industrial managed switch at backbone hub; optional — substitute with Ubiquiti USW-Flex-Mini at $89 for cost-reduced builds
B9: SECTION TOTAL | G9: =SUM(G3:G8)

Sheet Mechanical-Env
A1: Mechanical & Environmental — Enclosures, Mounting & Protection
A2: Line # | B2: Part Name | C2: Part Number / SKU | D2: Description | E2: Qty | F2: Unit Price (USD) | G2: Extended Price (USD) | H2: Supplier | I2: Supplier URL | J2: Lead Time | K2: Notes
A3: 1 | B3: Pelican 1550 Protector Case (IP67) | C3: 1550-000-110 | D3: 20.66×17.2×8.4in exterior, IP67, MIL-SPEC, Pick-N-Pluck foam, stainless hardware, lifetime guarantee | E3: 1 | F3: 332.95 | G3: =E3*F3 | H3: Pelican / CDW | I3: pelican.com | J3: In stock | K3: Primary mobile deployment enclosure for full compute + gateway stack
A4: 2 | B4: Pelican 1450 Protector Case (IP67) | C4: 1450-000-110 | D4: 15.43×10.93×6.93in exterior, IP67, Pick-N-Pluck foam, lighter profile | E4: 1 | F4: 175 | G4: =E4*F4 | H4: Pelican | I4: pelican.com | J4: In stock | K4: Smaller field node enclosure for Portenta + LoRa module remote units
A5: 3 | B5: Polycase WC-16-07 NEMA 4X Enclosure | C5: WC-16-07 | D5: 16×14×8in fiberglass NEMA 4X outdoor enclosure, UV-resistant, padlockable hasp, mounting plate | E5: 1 | F5: 95 | G5: =E5*F5 | H5: Polycase / Automation Direct | I5: polycase.com | J5: 5–7 days | K5: Fixed outdoor wall-mount enclosure for gateway + DIN-rail power components
A6: 4 | B6: DIN Rail TS-35 1m (pack of 2) | C6: Tripp Lite / Phoenix Contact | D6: Standard 35mm DIN rail, 1m length, zinc-plated steel, 2-pack | E6: 1 | F6: 16 | G6: =E6*F6 | H6: Amazon / Automation Direct | I6: automationdirect.com | J6: Next-day | K6: Mounts Mean Well PSU, fuse block, Teltonika router inside NEMA enclosure
A7: 5 | B7: Antenna Mast / Pole 2m Push-Up | C7: Max-Gain Systems or equiv. | D7: 2m threaded aluminum antenna mast, 1.25in OD, 10ft sections, guying kit included | E7: 1 | F7: 45 | G7: =E7*F7 | H7: Max-Gain Systems / Amazon | I7: amazon.com | J7: 5–7 days | K7: Elevates 8dBi gateway antenna above enclosure roofline
A8: 6 | B8: Cable Glands PG-16 IP68 (10-pack) | C8: Lapp Skintop / equiv. | D8: IP68 nylon cable glands, PG16, accepts 10–14mm OD cables, 10-pack | E8: 1 | F8: 14 | G8: =E8*F8 | H8: Amazon / Digi-Key | I8: digikey.com | J8: Next-day | K8: Weatherproof cable entry into NEMA / Pelican enclosures
A9: 7 | B9: Silica Gel Desiccant Packs 5g (20-pack) | C9: Eva-Dry 20-pack | D9: Indicating silica gel desiccant, 5g each, orange-to-green color change indicator, 20-pack | E9: 1 | F9: 10 | G9: =E9*F9 | H9: Amazon | I9: amazon.com | J9: Next-day | K9: Moisture control inside sealed enclosures; replace annually or when indicator changes
A10: 8 | B10: Anti-Vibration Rubber Isolators M4 (8-pack) | C10: Rocker / equiv. | D10: M4×20mm rubber anti-vibration standoffs, 8-pack, rated 5kg each | E10: 1 | F10: 12 | G10: =E10*F10 | H10: Amazon | I10: amazon.com | J10: Next-day | K10: Isolates SBCs from vibration when deployed in vehicles or on machinery
A11: 9 | B11: Stainless M3/M4 Hardware Assortment Kit | C11: Metric Hex Bolt Kit | D11: 400-piece M3/M4 SS hex bolts, nuts, washers, standoffs; fits most SBC PCB mounting | E11: 1 | F11: 18 | G11: =E11*F11 | H11: Amazon | I11: amazon.com | J11: Next-day | K11: General mechanical assembly fasteners
B12: SECTION TOTAL | G12: =SUM(G3:G11)
