Workbook

Sheet Summary Dashboard
A1: Sensor Species Family — BOM Summary Dashboard
A2: Project: Sculptural / Kinetic Art & Sensing Installation | Currency: CAD (estimated) | Location: Whitehorse, YT | Date: 2026-05-15
A4: COST BREAKDOWN BY CATEGORY
A5: Category | B5: Total Cost (CAD est.) | C5: % of Grand Total
A6: 3D Printed Parts (Materials) | B6: =BOM!J22 | C6: =IF(B17=0,"",B6/B17)
A7: Filaments | B7: =BOM!J32 | C7: =IF(B17=0,"",B7/B17)
A8: Printer Upgrades & Fab Equipment | B8: =BOM!J45 | C8: =IF(B17=0,"",B8/B17)
A9: Mechanical Hardware | B9: =BOM!J64 | C9: =IF(B17=0,"",B9/B17)
A10: Wire, Cable & Tendons | B10: =BOM!J76 | C10: =IF(B17=0,"",B10/B17)
A11: Electronics — Sensors | B11: =BOM!J87 | C11: =IF(B17=0,"",B11/B17)
A12: Electronics — Controllers & Computing | B12: =BOM!J97 | C12: =IF(B17=0,"",B12/B17)
A13: Electronics — Power | B13: =BOM!J108 | C13: =IF(B17=0,"",B13/B17)
A14: Electronics — Lighting & Effects | B14: =BOM!J116 | C14: =IF(B17=0,"",B14/B17)
A15: Connectors & Wiring Accessories | B15: =BOM!J129 | C15: =IF(B17=0,"",B15/B17)
A16: Consumables & Workshop Supplies | B16: =BOM!J151 | C16: =IF(B17=0,"",B16/B17)
A17: GRAND TOTAL — All Categories | B17: =SUM(B6:B16)
A19: PROJECT STATS
A20: Metric | B20: Value
A21: Total Unique Line Items | B21: 106
A22: Critical Priority Items | B22: 57
A23: Recommended Priority Items | B23: =COUNTIF(BOM!L:L,"Recommended")
A24: Optional Priority Items | B24: =COUNTIF(BOM!L:L,"Optional")
A25: Items To Order | B25: =COUNTIF(BOM!M:M,"To Order")
A26: Items In Stock | B26: =COUNTIF(BOM!M:M,"In Stock")
A27: Items Ordered | B27: =COUNTIF(BOM!M:M,"Ordered")
A28: Estimated Grand Total (CAD) | B28: =B17
A30: PROJECT NOTES
A31: • All costs are CAD estimates as of May 2026; prices may vary by supplier and availability in Whitehorse, YT.
A32: • 3D printing filament costs are estimated at material cost only (electricity + machine wear not included).
A33: • Priority: CRITICAL = project cannot proceed without; RECOMMENDED = strongly advised; OPTIONAL = nice-to-have.
A34: • Status: 'To Order' items should be sourced first. Consider bulk fastener orders from Bolt Depot or Fastenal.
A35: • Whitehorse sourcing: Electronics may require online ordering (Adafruit, Digikey). Budget extra for shipping to YT.
A36: • Cross-reference BOM Item # against your 3D print job queue and assembly notes for each morphology sub-system.
A37: • PETG-CF and ASA filaments require hardened nozzle + enclosure — ensure printer upgrades are received first.
A38: • Sensor node count: 6× Pico W + 4× QT Py RP2040 + 1× RPi 4B central hub. Verify I2C address conflicts before assembly.

Sheet BOM
A1: Sensor Species Family — Full Bill of Materials
A2: Project: Sculptural / Kinetic Art & Sensing Installation | Currency: CAD (estimated) | Generated: 2026-05-15
A3: SECTION 1 — MORPHOLOGY COMPONENTS: 3D PRINTED PARTS
A4: Item # | B4: Component Name | C4: Description / Notes | D4: Category | E4: Morphology / Assembly | F4: Material or Spec | G4: Qty | H4: Unit | I4: Unit Cost (CAD est.) | J4: Total Cost (CAD) | K4: Supplier / Source | L4: Priority | M4: Status
A5: 1 | B5: Pollen Pod Shell | C5: Main sensor housing capsule — ovoid shell, two-part clamshell | D5: 3D Printed Parts | E5: Pollen Pod | F5: PETG or ABS, ~45g/pod | G5: 6 | H5: ea | I5: 3.5 | J5: =IF(G5="","",G5*I5) | K5: 3D Print in-house / Filament cost | L5: Critical | M5: To Order
A6: 2 | B6: Pollen Pod Vent Ring | C6: Parametric lattice insert for airflow/venting | D6: 3D Printed Parts | E6: Pollen Pod | F6: TPU 95A, ~8g each | G6: 6 | H6: ea | I6: 1.2 | J6: =IF(G6="","",G6*I6) | K6: 3D Print in-house / Filament cost | L6: Recommended | M6: To Order
A7: 3 | B7: Pollen Pod Mounting Flange | C7: M3 heat-set insert collar for pod attachment | D7: 3D Printed Parts | E7: Pollen Pod | F7: PETG, ~5g each | G7: 6 | H7: ea | I7: 0.8 | J7: =IF(G7="","",G7*I7) | K7: 3D Print in-house / Filament cost | L7: Critical | M7: To Order
A8: 4 | B8: Garland Link Body | C8: Articulating chain link body, oval form with pivot bore | D8: 3D Printed Parts | E8: Garland Links | F8: PETG, ~12g each | G8: 48 | H8: ea | I8: 0.9 | J8: =IF(G8="","",G8*I8) | K8: 3D Print in-house / Filament cost | L8: Critical | M8: To Order
A9: 5 | B9: Garland End Cap | C9: Capped terminus link with cable pass-through | D9: 3D Printed Parts | E9: Garland Links | F9: PETG, ~9g each | G9: 12 | H9: ea | I9: 0.8 | J9: =IF(G9="","",G9*I9) | K9: 3D Print in-house / Filament cost | L9: Critical | M9: To Order
A10: 6 | B10: Garland Spacer Ring | C10: Inter-link spacing washer | D10: 3D Printed Parts | E10: Garland Links | F10: TPU 85A, ~2g each | G10: 48 | H10: ea | I10: 0.3 | J10: =IF(G10="","",G10*I10) | K10: 3D Print in-house / Filament cost | L10: Recommended | M10: To Order
A11: 7 | B11: Tendon Routing Cleat | C11: Cable anchor with groove for tendon management | D11: 3D Printed Parts | E11: Tendons | F11: PETG, ~6g each | G11: 24 | H11: ea | I11: 0.7 | J11: =IF(G11="","",G11*I11) | K11: 3D Print in-house / Filament cost | L11: Critical | M11: To Order
A12: 8 | B12: Tendon Tensioner Body | C12: Spring-loaded adjuster housing for tendon tension | D12: 3D Printed Parts | E12: Tendons | F12: PETG, ~18g each | G12: 12 | H12: ea | I12: 1.6 | J12: =IF(G12="","",G12*I12) | K12: 3D Print in-house / Filament cost | L12: Critical | M12: To Order
A13: 9 | B13: Tendon Pulley Wheel | C13: Small flanged wheel, 8mm bore, for tendon routing | D13: 3D Printed Parts | E13: Tendons | F13: PETG or PLA, ~7g each | G13: 24 | H13: ea | I13: 0.7 | J13: =IF(G13="","",G13*I13) | K13: 3D Print in-house / Filament cost | L13: Critical | M13: To Order
A14: 10 | B14: Perch Pod Main Body | C14: Sensor nest / mounting platform | D14: 3D Printed Parts | E14: Perch Pods | F14: PETG, ~60g each | G14: 4 | H14: ea | I14: 4.5 | J14: =IF(G14="","",G14*I14) | K14: 3D Print in-house / Filament cost | L14: Critical | M14: To Order
A15: 11 | B15: Perch Pod Canopy | C15: Dome cover with diffuser aperture | D15: 3D Printed Parts | E15: Perch Pods | F15: Clear PETG or PETG-CF, ~22g | G15: 4 | H15: ea | I15: 2.2 | J15: =IF(G15="","",G15*I15) | K15: 3D Print in-house / Filament cost | L15: Critical | M15: To Order
A16: 12 | B16: Perch Pod Base Bracket | C16: Wall/rod mounting interface bracket | D16: 3D Printed Parts | E16: Perch Pods | F16: PETG, ~15g each | G16: 4 | H16: ea | I16: 1.4 | J16: =IF(G16="","",G16*I16) | K16: 3D Print in-house / Filament cost | L16: Critical | M16: To Order
... A21: 17 | B21: Drift Fin | C21: Thin curved stabilizer fin for hanging balance | D21: 3D Printed Parts | E21: Garland Extras | F21: PETG-CF, ~10g each | G21: 16 | H21: ea | I21: 1 | J21: =IF(G21="","",G21*I21) | K21: 3D Print in-house / Filament cost | L21: Optional | M21: To Order
A22: SUBTOTAL — 3D Printed Parts | J22: =SUM(J5:J21)
A24: SECTION 2 — FILAMENTS
A25: Item # | B25: Component Name | C25: Description / Notes | D25: Category | E25: Morphology / Assembly | F25: Material or Spec | G25: Qty | H25: Unit | I25: Unit Cost (CAD est.) | J25: Total Cost (CAD) | K25: Supplier / Source | L25: Priority | M25: Status
A26: 18 | B26: PETG Standard Filament | C26: Black, white, and natural/translucent — standard structural filament | D26: Filaments | E26: All Print Morphologies | F26: PETG 1.75mm 1kg spool | G26: 3 | H26: spool | I26: 34 | J26: =IF(G26="","",G26*I26) | K26: Prusa/MatterHackers/Amazon | L26: Critical | M26: To Order
A27: 19 | B27: TPU 95A Flexible Filament | C27: Black flexible filament for vent rings and edge trim | D27: Filaments | E27: Vent Rings / Edge Trim | F27: TPU 95A 1.75mm 0.5kg spool | G27: 2 | H27: spool | I27: 28 | J27: =IF(G27="","",G27*I27) | K27: Prusa/eSUN/Amazon | L27: Critical | M27: To Order
A28: 20 | B28: TPU 85A Ultra-Flex Filament | C28: Black ultra-flex for garland spacer rings | D28: Filaments | E28: Spacer Rings | F28: TPU 85A 1.75mm 0.5kg spool | G28: 1 | H28: spool | I28: 30 | J28: =IF(G28="","",G28*I28) | K28: Prusa/eSUN/Amazon | L28: Critical | M28: To Order
A29: 21 | B29: Clear PETG Filament | C29: Transparent — for canopy diffuser optics | D29: Filaments | E29: Perch Pod Canopy | F29: Clear PETG 1.75mm 1kg spool | G29: 1 | H29: spool | I29: 38 | J29: =IF(G29="","",G29*I29) | K29: Prusa/MatterHackers/Amazon | L29: Critical | M29: To Order
A30: 22 | B30: PETG-CF Carbon Fiber Filament | C30: Carbon fiber reinforced PETG for drift fins and structural parts | D30: Filaments | E30: Drift Fins / Rigid Parts | F30: PETG-CF 1.75mm 0.5kg spool | G30: 1 | H30: spool | I30: 55 | J30: =IF(G30="","",G30*I30) | K30: Prusa/Polymaker/Amazon | L30: Recommended | M30: To Order
A31: 23 | B31: ASA UV-Resistant Filament | C31: UV-stable outdoor-grade filament, grey or black | D31: Filaments | E31: Reef Plates | F31: ASA 1.75mm 1kg spool | G31: 1 | H31: spool | I31: 40 | J31: =IF(G31="","",G31*I31) | K31: Prusa/eSUN/Amazon | L31: Recommended | M31: To Order
A32: SUBTOTAL — Filaments | J32: =SUM(J26:J31)
A34: SECTION 3 — PRINTER UPGRADES & FABRICATION EQUIPMENT
A35: Item # | B35: Component Name | C35: Description / Notes | D35: Category | E35: Morphology / Assembly | F35: Material or Spec | G35: Qty | H35: Unit | I35: Unit Cost (CAD est.) | J35: Total Cost (CAD) | K35: Supplier / Source | L35: Priority | M35: Status
A36: 24 | B36: Hardened Steel Nozzle 0.4mm | C36: For carbon fiber filaments; resists abrasive wear | D36: Printer Upgrades | E36: Printer Hardware | F36: Hardened steel, 0.4mm | G36: 3 | H36: ea | I36: 12 | J36: =IF(G36="","",G36*I36) | K36: E3D / Trianglelab / Amazon | L36: Critical | M36: To Order
A37: 25 | B37: Hardened Steel Nozzle 0.6mm | C37: For faster structural prints; wider extrusion | D37: Printer Upgrades | E37: Printer Hardware | F37: Hardened steel, 0.6mm | G37: 2 | H37: ea | I37: 13 | J37: =IF(G37="","",G37*I37) | K37: E3D / Trianglelab / Amazon | L37: Recommended | M37: To Order
A38: 26 | B38: All-Metal Hotend Upgrade Kit | C38: For high-temp PETG/ASA printing up to 300°C | D38: Printer Upgrades | E38: Printer Hardware | F38: All-metal, 300°C rated | G38: 1 | H38: kit | I38: 55 | J38: =IF(G38="","",G38*I38) | K38: E3D / Micro Swiss / Amazon | L38: Critical | M38: To Order
A39: 27 | B39: Direct Drive Extruder Upgrade Kit | C39: Direct drive conversion for better flex-filament control | D39: Printer Upgrades | E39: Printer Hardware | F39: Direct drive kit | G39: 1 | H39: kit | I39: 75 | J39: =IF(G39="","",G39*I39) | K39: Bondtech / Trianglelab / Amazon | L39: Recommended | M39: To Order
A40: 28 | B40: PEI Spring Steel Magnetic Build Plate | C40: Magnetic flex plate with PEI surface, 235x235mm | D40: Printer Upgrades | E40: Printer Hardware | F40: PEI spring steel, 235x235mm | G40: 2 | H40: ea | I40: 28 | J40: =IF(G40="","",G40*I40) | K40: Prusa / Energetic / Amazon | L40: Recommended | M40: To Order
A41: 29 | B41: Filament Drybox w/ Humidity Control | C41: Active drybox for moisture-sensitive filaments (TPU, PA, CF) | D41: Printer Upgrades | E41: Fab Equipment | F41: Drybox with hygrometer | G41: 1 | H41: ea | I41: 45 | J41: =IF(G41="","",G41*I41) | K41: Sunlu / Eibos / Amazon | L41: Critical | M41: To Order
A42: 30 | B42: Filament Moisture Sensor/Hygrometer | C42: Monitor humidity in drybox/storage | D42: Printer Upgrades | E42: Fab Equipment | F42: Digital hygrometer | G42: 2 | H42: ea | I42: 12 | J42: =IF(G42="","",G42*I42) | K42: Amazon / local hardware | L42: Recommended | M42: To Order
A43: 31 | B43: PTFE Bowden Tube | C43: Replacement tube 4mm OD 2mm ID, 3m length | D43: Printer Upgrades | E43: Printer Hardware | F43: PTFE, 4mm OD / 2mm ID, 3m | G43: 1 | H43: length | I43: 8 | J43: =IF(G43="","",G43*I43) | K43: Capricorn / Amazon | L43: Recommended | M43: To Order
A44: 32 | B44: Printer Enclosure Kit/DIY Panels | C44: Enclosure for controlled printing environment — required for ASA | D44: Printer Upgrades | E44: Fab Equipment | F44: Enclosure panels or kit | G44: 1 | H44: kit | I44: 80 | J44: =IF(G44="","",G44*I44) | K44: IKEA Lack mod / Creality / DIY | L44: Critical | M44: To Order
A45: SUBTOTAL — Printer Upgrades & Fabrication Equipment | J45: =SUM(J36:J44)
A47: SECTION 4 — MECHANICAL HARDWARE: FASTENERS & STRUCTURAL
A48: Item # | B48: Component Name | C48: Description / Notes | D48: Category | E48: Morphology / Assembly | F48: Material or Spec | G48: Qty | H48: Unit | I48: Unit Cost (CAD est.) | J48: Total Cost (CAD) | K48: Supplier / Source | L48: Priority | M48: Status
A49: 33 | B49: M3x8mm SHCS Stainless | C49: Socket head cap screw M3x8mm stainless steel | D49: Mechanical Hardware | E49: Fasteners | F49: M3x8 SHCS, 316 SS | G49: 100 | H49: ea | I49: 0.08 | J49: =IF(G49="","",G49*I49) | K49: Bolt Depot / Fastenal / Amazon | L49: Critical | M49: In Stock
A50: 34 | B50: M3x12mm SHCS Stainless | C50: Socket head cap screw M3x12mm stainless steel | D50: Mechanical Hardware | E50: Fasteners | F50: M3x12 SHCS, 316 SS | G50: 60 | H50: ea | I50: 0.09 | J50: =IF(G50="","",G50*I50) | K50: Bolt Depot / Fastenal / Amazon | L50: Critical | M50: To Order
A51: 35 | B51: M3x20mm SHCS Stainless | C51: Socket head cap screw M3x20mm stainless steel | D51: Mechanical Hardware | E51: Fasteners | F51: M3x20 SHCS, 316 SS | G51: 40 | H51: ea | I51: 0.1 | J51: =IF(G51="","",G51*I51) | K51: Bolt Depot / Fastenal / Amazon | L51: Critical | M51: To Order
A52: 36 | B52: M3 Hex Nut Stainless | C52: Standard M3 hex nut, stainless steel | D52: Mechanical Hardware | E52: Fasteners | F52: M3 hex nut, 316 SS | G52: 120 | H52: ea | I52: 0.06 | J52: =IF(G52="","",G52*I52) | K52: Bolt Depot / Fastenal / Amazon | L52: Critical | M52: To Order
A53: 37 | B53: M3 Washer Stainless | C53: Standard M3 flat washer, stainless steel | D53: Mechanical Hardware | E53: Fasteners | F53: M3 washer, 316 SS | G53: 120 | H53: ea | I53: 0.05 | J53: =IF(G53="","",G53*I53) | K53: Bolt Depot / Fastenal / Amazon | L53: Critical | M53: To Order
A54: 38 | B54: M3x4.6mm Heat-Set Inserts | C54: Brass heat-set threaded inserts for PETG parts | D54: Mechanical Hardware | E54: Fasteners | F54: M3x4.6mm brass heat-set | G54: 150 | H54: ea | I54: 0.18 | J54: =IF(G54="","",G54*I54) | K54: CNC Kitchen / Amazon / 3Dmakerworld | L54: Critical | M54: To Order
A55: 39 | B55: M2x6mm SHCS Stainless | C55: Socket head cap screw M2x6mm stainless steel | D55: Mechanical Hardware | E55: Fasteners | F55: M2x6 SHCS, 316 SS | G55: 60 | H55: ea | I55: 0.07 | J55: =IF(G55="","",G55*I55) | K55: Bolt Depot / Fastenal / Amazon | L55: Recommended | M55: To Order
A56: 40 | B56: M2 Hex Nut Stainless | C56: Standard M2 hex nut, stainless steel | D56: Mechanical Hardware | E56: Fasteners | F56: M2 hex nut, 316 SS | G56: 60 | H56: ea | I56: 0.05 | J56: =IF(G56="","",G56*I56) | K56: Bolt Depot / Fastenal / Amazon | L56: Recommended | M56: To Order
A57: 41 | B57: M4x16mm SHCS Stainless | C57: Socket head cap screw M4x16mm stainless steel | D57: Mechanical Hardware | E57: Fasteners | F57: M4x16 SHCS, 316 SS | G57: 30 | H57: ea | I57: 0.12 | J57: =IF(G57="","",G57*I57) | K57: Bolt Depot / Fastenal / Amazon | L57: Recommended | M57: To Order
A58: 42 | B58: M4 Hex Nut Stainless | C58: Standard M4 hex nut, stainless steel | D58: Mechanical Hardware | E58: Fasteners | F58: M4 hex nut, 316 SS | G58: 30 | H58: ea | I58: 0.07 | J58: =IF(G58="","",G58*I58) | K58: Bolt Depot / Fastenal / Amazon | L58: Recommended | M58: To Order
A59: 43 | B59: M4 Washer Stainless | C59: Standard M4 flat washer, stainless steel | D59: Mechanical Hardware | E59: Fasteners | F59: M4 washer, 316 SS | G59: 30 | H59: ea | I59: 0.06 | J59: =IF(G59="","",G59*I59) | K59: Bolt Depot / Fastenal / Amazon | L59: Recommended | M59: To Order
A60: 44 | B60: 8mm Steel Shaft Rod 200mm | C60: Pivot axle rods for garland links, 200mm length | D60: Mechanical Hardware | E60: Structural | F60: 8mm dia steel, 200mm | G60: 6 | H60: ea | I60: 3.2 | J60: =IF(G60="","",G60*I60) | K60: Metal Supermarkets / Amazon | L60: Critical | M60: To Order
... A63: 47 | B63: Compression Spring 8mm OD 20mm | C63: Medium tension compression spring for tendon tensioners | D63: Mechanical Hardware | E63: Structural | F63: 8mm OD / 20mm L, med tension | G63: 12 | H63: ea | I63: 0.8 | J63: =IF(G63="","",G63*I63) | K63: Specs / Amazon / McMaster-Carr | L63: Critical | M63: To Order
A64: SUBTOTAL — Mechanical Hardware | J64: =SUM(J49:J63)
A66: SECTION 5 — WIRE, CABLE & TENDONS
A67: Item # | B67: Component Name | C67: Description / Notes | D67: Category | E67: Morphology / Assembly | F67: Material or Spec | G67: Qty | H67: Unit | I67: Unit Cost (CAD est.) | J67: Total Cost (CAD) | K67: Supplier / Source | L67: Priority | M67: Status
A68: 48 | B68: Spectra/Dyneema Fishing Line 0.4mm | C68: Primary tendon material, 20lb breaking strength | D68: Wire & Cable | E68: Tendons | F68: 0.4mm, 20lb, 100m spool | G68: 1 | H68: spool | I68: 18 | J68: =IF(G68="","",G68*I68) | K68: Amazon / fishing supply | L68: Critical | M68: To Order
A69: 49 | B69: Stainless Steel Wire Rope 0.8mm | C69: Structural rigging wire, 30m reel | D69: Wire & Cable | E69: Rigging | F69: 0.8mm SS wire rope, 30m | G69: 1 | H69: reel | I69: 22 | J69: =IF(G69="","",G69*I69) | K69: Amazon / rigging supply | L69: Critical | M69: To Order
A70: 50 | B70: Silicone Wire 28AWG Ribbon | C70: Multicore ribbon for signal runs, silicone jacketed | D70: Wire & Cable | E70: Signal Wiring | F70: 28AWG silicone multicore ribbon, 10m | G70: 1 | H70: m | I70: 16 | J70: =IF(G70="","",G70*I70) | K70: Adafruit / Amazon | L70: Critical | M70: To Order
A71: 51 | B71: Silicone Wire 24AWG Red | C71: Power run wiring, red, 10m | D71: Wire & Cable | E71: Power Wiring | F71: 24AWG silicone, red, 10m | G71: 1 | H71: reel | I71: 10 | J71: =IF(G71="","",G71*I71) | K71: Adafruit / Amazon | L71: Critical | M71: To Order
A72: 52 | B72: Silicone Wire 24AWG Black | C72: Power run wiring, black, 10m | D72: Wire & Cable | E72: Power Wiring | F72: 24AWG silicone, black, 10m | G72: 1 | H72: reel | I72: 10 | J72: =IF(G72="","",G72*I72) | K72: Adafruit / Amazon | L72: Critical | M72: To Order
A73: 53 | B73: Heat Shrink Tubing Assortment | C73: 2mm/3mm/5mm/8mm sizes for wire terminations | D73: Wire & Cable | E73: Cable Mgmt | F73: 2/3/5/8mm assortment kit | G73: 1 | H73: kit | I73: 12 | J73: =IF(G73="","",G73*I73) | K73: Amazon | L73: Critical | M73: To Order
A74: 54 | B74: Cable Spiral Wrap 6mm | C74: Harness management spiral wrap, 5m | D74: Wire & Cable | E74: Cable Mgmt | F74: 6mm dia, 5m | G74: 1 | H74: reel | I74: 8 | J74: =IF(G74="","",G74*I74) | K74: Amazon | L74: Recommended | M74: To Order
A75: 55 | B75: Zip Ties Assortment Small/Medium | C75: Cable bundling and routing, 200pc assortment | D75: Wire & Cable | E75: Cable Mgmt | F75: Small/medium, 200pc | G75: 1 | H75: pack | I75: 8 | J75: =IF(G75="","",G75*I75) | K75: Amazon / local hardware | L75: Recommended | M75: In Stock
A76: SUBTOTAL — Wire, Cable & Tendons | J76: =SUM(J68:J75)
A78: SECTION 6 — ELECTRONICS: SENSORS
A79: Item # | B79: Component Name | C79: Description / Notes | D79: Category | E79: Morphology / Assembly | F79: Material or Spec | G79: Qty | H79: Unit | I79: Unit Cost (CAD est.) | J79: Total Cost (CAD) | K79: Supplier / Source | L79: Priority | M79: Status
A80: 56 | B80: BME280 Sensor Breakout | C80: Temp / humidity / pressure sensor breakout board | D80: Electronics – Sensors | E80: Pollen Pods / Perch Pods | F80: BME280 I2C/SPI breakout | G80: 8 | H80: ea | I80: 12 | J80: =IF(G80="","",G80*I80) | K80: Adafruit / Sparkfun / Amazon | L80: Critical | M80: To Order
A81: 57 | B81: TSL2591 Light Sensor Breakout | C81: High-dynamic-range lux/light sensor breakout | D81: Electronics – Sensors | E81: Pollen Pods | F81: TSL2591 I2C breakout | G81: 6 | H81: ea | I81: 14 | J81: =IF(G81="","",G81*I81) | K81: Adafruit / Amazon | L81: Critical | M81: To Order
A82: 58 | B82: APDS-9960 Gesture/Proximity/Color | C82: Gesture, proximity, and color sensing breakout | D82: Electronics – Sensors | E82: Perch Pods / Garland | F82: APDS-9960 I2C breakout | G82: 4 | H82: ea | I82: 15 | J82: =IF(G82="","",G82*I82) | K82: Adafruit / Sparkfun / Amazon | L82: Recommended | M82: To Order
A83: 59 | B83: PIR Motion Sensor HC-SR501 | C83: Passive infrared motion sensor for perch pods | D83: Electronics – Sensors | E83: Perch Pods | F83: HC-SR501 PIR module | G83: 4 | H83: ea | I83: 4.5 | J83: =IF(G83="","",G83*I83) | K83: Amazon / Adafruit | L83: Critical | M83: To Order
A84: 60 | B84: Electret Mic Amp Breakout | C84: MAX4466 or MAX9814 microphone amplifier breakout | D84: Electronics – Sensors | E84: Pollen Pods / Reef | F84: MAX4466 or MAX9814 breakout | G84: 4 | H84: ea | I84: 9 | J84: =IF(G84="","",G84*I84) | K84: Adafruit / Amazon | L84: Recommended | M84: To Order
A85: 61 | B85: Capacitive Soil/Touch Sensor | C85: Capacitive sensor for pollen pod interactivity | D85: Electronics – Sensors | E85: Pollen Pods | F85: Capacitive soil/touch module | G85: 6 | H85: ea | I85: 5 | J85: =IF(G85="","",G85*I85) | K85: Adafruit / Amazon | L85: Recommended | M85: To Order
A86: 62 | B86: Piezo Vibration Sensor Disc 27mm | C86: 27mm piezo disc for garland link resonance sensing | D86: Electronics – Sensors | E86: Garland Links | F86: 27mm piezo disc | G86: 12 | H86: ea | I86: 2.5 | J86: =IF(G86="","",G86*I86) | K86: Adafruit / Digikey / Amazon | L86: Optional | M86: To Order
A87: SUBTOTAL — Electronics: Sensors | J87: =SUM(J80:J86)
A89: SECTION 7 — ELECTRONICS: CONTROLLERS & COMPUTING
A90: Item # | B90: Component Name | C90: Description / Notes | D90: Category | E90: Morphology / Assembly | F90: Material or Spec | G90: Qty | H90: Unit | I90: Unit Cost (CAD est.) | J90: Total Cost (CAD) | K90: Supplier / Source | L90: Priority | M90: Status
A91: 63 | B91: Raspberry Pi Pico W | C91: WiFi-enabled MCU for distributed sensor nodes | D91: Electronics – Controllers | E91: Sensor Nodes | F91: RP2040 + WiFi, Pico W | G91: 6 | H91: ea | I91: 12 | J91: =IF(G91="","",G91*I91) | K91: Adafruit / Digikey / PiShop.ca | L91: Critical | M91: To Order
A92: 64 | B92: Raspberry Pi 4B 4GB | C92: Central hub and processing node | D92: Electronics – Controllers | E92: Central Hub | F92: RPi 4B 4GB RAM | G92: 1 | H92: ea | I92: 90 | J92: =IF(G92="","",G92*I92) | K92: PiShop.ca / Canakit | L92: Critical | M92: To Order
A93: 65 | B93: Adafruit QT Py RP2040 | C93: Compact node controller for tight spaces | D93: Electronics – Controllers | E93: Compact Nodes | F93: QT Py RP2040 | G93: 4 | H93: ea | I93: 14 | J93: =IF(G93="","",G93*I93) | K93: Adafruit / Digikey | L93: Recommended | M93: To Order
A94: 66 | B94: FeatherWing Proto Board | C94: Custom or Adafruit proto featherwing for node wiring | D94: Electronics – Controllers | E94: Node Wiring | F94: Adafruit FeatherWing Proto | G94: 6 | H94: ea | I94: 8 | J94: =IF(G94="","",G94*I94) | K94: Adafruit | L94: Recommended | M94: To Order
A95: 67 | B95: MicroSD Card 32GB | C95: Data logging for Pi hub | D95: Electronics – Controllers | E95: Central Hub | F95: 32GB MicroSD Class 10 | G95: 2 | H95: ea | I95: 10 | J95: =IF(G95="","",G95*I95) | K95: Amazon / BestBuy | L95: Recommended | M95: To Order
A96: 68 | B96: USB-C PD Board 5V 3A | C96: Per-node USB-C power delivery board | D96: Electronics – Controllers | E96: Power Interface | F96: 5V/3A USB-C PD board | G96: 6 | H96: ea | I96: 8 | J96: =IF(G96="","",G96*I96) | K96: Adafruit / Amazon | L96: Critical | M96: To Order
A97: SUBTOTAL — Electronics: Controllers & Computing | J97: =SUM(J91:J96)
A99: SECTION 8 — ELECTRONICS: POWER
A100: Item # | B100: Component Name | C100: Description / Notes | D100: Category | E100: Morphology / Assembly | F100: Material or Spec | G100: Qty | H100: Unit | I100: Unit Cost (CAD est.) | J100: Total Cost (CAD) | K100: Supplier / Source | L100: Priority | M100: Status
A101: 69 | B101: 5V 10A Switching Power Supply | C101: Central power supply, 50W, 5V | D101: Electronics – Power | E101: Central Power | F101: 5V 10A AC-DC switching PSU | G101: 1 | H101: ea | I101: 35 | J101: =IF(G101="","",G101*I101) | K101: Amazon / Digikey | L101: Critical | M101: To Order
A102: 70 | B102: USB Power Hub 7-Port | C102: 7-port USB hub with per-port switching for nodes | D102: Electronics – Power | E102: Node Power | F102: 7-port USB hub, per-port switch | G102: 1 | H102: ea | I102: 28 | J102: =IF(G102="","",G102*I102) | K102: Amazon | L102: Critical | M102: To Order
A103: 71 | B103: LiPo Battery 3.7V 2000mAh | C103: Portable/backup power for nodes | D103: Electronics – Power | E103: Backup Power | F103: 3.7V 2000mAh LiPo | G103: 4 | H103: ea | I103: 14 | J103: =IF(G103="","",G103*I103) | K103: Adafruit / Amazon | L103: Recommended | M103: To Order
A104: 72 | B104: LiPo Charger/Protection TP4056 | C104: Charging and protection board for LiPo cells | D104: Electronics – Power | E104: Backup Power | F104: TP4056 1A charger/protector | G104: 4 | H104: ea | I104: 2.5 | J104: =IF(G104="","",G104*I104) | K104: Amazon | L104: Recommended | M104: To Order
A105: 73 | B105: DC-DC Buck Converter 12V to 5V 3A | C105: Step-down converter for nodes on 12V rail | D105: Electronics – Power | E105: Node Power | F105: 12V→5V 3A buck converter | G105: 4 | H105: ea | I105: 6 | J105: =IF(G105="","",G105*I105) | K105: Amazon / Pololu | L105: Recommended | M105: To Order
A106: 74 | B106: Power Distribution Bus Bar | C106: Terminal block bus bar for power distribution | D106: Electronics – Power | E106: Power Distrib. | F106: Bus bar / terminal block | G106: 2 | H106: ea | I106: 10 | J106: =IF(G106="","",G106*I106) | K106: Amazon / Digikey | L106: Critical | M106: To Order
A107: 75 | B107: Inline Fuse Holder with 2A Fuses | C107: Fused protection on individual branches | D107: Electronics – Power | E107: Power Distrib. | F107: Inline blade fuse holder, 2A | G107: 8 | H107: ea | I107: 1.5 | J107: =IF(G107="","",G107*I107) | K107: Amazon / automotive supply | L107: Critical | M107: To Order
A108: SUBTOTAL — Electronics: Power | J108: =SUM(J101:J107)
A110: SECTION 9 — ELECTRONICS: LIGHTING & EFFECTS
A111: Item # | B111: Component Name | C111: Description / Notes | D111: Category | E111: Morphology / Assembly | F111: Material or Spec | G111: Qty | H111: Unit | I111: Unit Cost (CAD est.) | J111: Total Cost (CAD) | K111: Supplier / Source | L111: Priority | M111: Status
A112: 76 | B112: WS2812B LED Strip 60LED/m 5m | C112: Addressable RGB LED strip, 5m reel, 60 LED/m | D112: Electronics – Lighting | E112: Garland / Reef | F112: WS2812B 60LED/m, 5m reel | G112: 1 | H112: reel | I112: 35 | J112: =IF(G112="","",G112*I112) | K112: Amazon / Adafruit | L112: Critical | M112: To Order
A113: 77 | B113: WS2812B LED Ring 16-pixel | C113: Addressable RGB ring for pollen pod accent lighting | D113: Electronics – Lighting | E113: Pollen Pods | F113: WS2812B 16-pixel ring | G113: 6 | H113: ea | I113: 8 | J113: =IF(G113="","",G113*I113) | K113: Amazon / Adafruit | L113: Critical | M113: To Order
A114: 78 | B114: NeoPixel Jewel 7-pixel | C114: 7-pixel NeoPixel for perch pod canopy diffuser | D114: Electronics – Lighting | E114: Perch Pod Canopy | F114: Adafruit NeoPixel Jewel 7px | G114: 4 | H114: ea | I114: 9 | J114: =IF(G114="","",G114*I114) | K114: Adafruit | L114: Critical | M114: To Order
...
